{
  "translations": {
    "en": {
      "navigation": {
        "home": "Home",
        "about": "About",
        "notes": "Notes"
      },

      "button": {
        "submit": "submit",
        "cancel": "cancel",
        "save": "save",
        "create": "create",
        "add": "add",
        "edit": "edit",
        "update": "update",
        "back": "back",
        "open": "open",
        "close": "close",
        "delete": "delete",
        "reset": "reset"
      },

      "form": {
        "required": "Required",
        "optional": "Optional",
        "header": "Form",
        "subheader": {
          "add": "Add new note",
          "edit": "Edit note",
          "background": "Set background color"
        },
        "title": {
          "label": "Title",
          "placeholder": "Note title",
          "error": "Please enter a title"
        },
        "note": {
          "label": "Note",
          "placeholder": "Your note",
          "error": "Please enter a note"
        }
      },

      "validation": {
        "charsNotAllowed": "You entered disallowed characters",
        "minCharsTitle": "Please enter at least 5 characters",
        "minCharsContent": "Please enter at least 15 characters",
        "correctTitle": "Please enter a note title",
        "correctContent": "Please enter some content"
      },

      "toast": {
        "toastNoData": "Note could not be found.",
        "toastDataSaved": "Note stored.",
        "toastDataDeleted": "Note deleted.",
        "toastDataError": "An error occurred."
      },

      "dialog": {
        "header": {
          "delete": "Delete the current note"
        },
        "body": {
          "delete": "You will not be able to recover this"
        }
      },

      "hint": {
        "header": "No data available",
        "content": "No info available. Please check back later."
      },

      "footer": {
        "copyright": "Stefan Blattmann 2018."
      }
    }
  }
}
